test-designs/test_2.v
module place_holder (
  input  CLK,
  input  RST,
  output reg [31:0] out 
);
  
  wire [31:0] out_wire; 
  //wire [31:0] out_wire1; 
  initial begin
    out = 0;
  end
  
  always @(posedge CLK) begin
    if (RST) begin
      out <= 0;
    end
    else begin
      out <= out + 1;
    end
  end
  
  place_holder_2 test_1(
    .CLK (CLK),
    .RST (RST),
    .out (out_wire)
  );

  //place_holder_2 test_2(
  //  .CLK (CLK),
  //  .RST (RST),
  //  .out (out_wire1)
  //);
  
endmodule

module place_holder_2 (
  input  CLK,
  input  RST,
  output reg [31:0] out 
);
  initial begin
    out = 0;
  end
  
  always @(posedge CLK) begin
    if (RST) begin
      out <= 0;
    end
    else begin
      out <= out + 1;
    end
    assert (out <= 14);
    //assert (out <= 2) else begin
    //  $error("Assertion failed: out is not even!");
    //end
  end
    
endmodule

// 验证模块
//module place_holder_props (
//  input CLK,
//  input RST,
//  input [31:0] out,
//  input [31:0] out_wire
//);
//
//  // ------------------------------------------
//  // 辅助逻辑：记录复位后的周期数
//  // ------------------------------------------
//  reg [31:0] cycle_cnt;
//  
//  always @(posedge CLK) begin
//    if (RST) begin
//      cycle_cnt <= 0;
//    end else begin
//      cycle_cnt <= cycle_cnt + 1;
//    end
//  end
//
//  // ------------------------------------------
//  // Property 1: 验证 out 必须等于 cycle_cnt 的平方
//  // ------------------------------------------
//  property p_square_function;
//    @(posedge CLK) disable iff (RST)
//    // 只有在没有溢出的范围内验证，避免32位溢出误报
//    (cycle_cnt < 65535) |-> (out == cycle_cnt * cycle_cnt);
//  endproperty
//
//  assert_square: assert property (p_square_function)
//    else $error("[ASSERT FAIL] out is not square of cycles! out=%0d, cycle=%0d", out, cycle_cnt);
//
//  // ------------------------------------------
//  // Property 2: 验证子模块 out_wire 始终是偶数
//  // ------------------------------------------
//  property p_wire_even;
//    @(posedge CLK) disable iff (RST)
//    (out_wire[0] == 1'b0);
//  endproperty
//
//  assert_even: assert property (p_wire_even)
//    else $error("[ASSERT FAIL] out_wire should be even!");
//
//endmodule
//
//// 绑定语句 (放在 testbench 或此时即可)
//bind place_holder place_holder_props u_sva (.*);

test-designs/test_2/test_2_prove/engine_0/trace_induct.vcd
$version Generated by Yosys-SMTBMC $end
$timescale 1ns $end
$var integer 32 t smt_step $end
$var event 1 ! smt_clock $end
$scope module place_holder $end
$var wire 1 n0 CLK $end
$var wire 1 n1 RST $end
$var wire 32 n2 out $end
$var wire 32 n3 out_wire $end
$scope module test_1 $end
$var wire 1 n4 CLK $end
$var wire 1 n5 RST $end
$var wire 32 n6 out $end
$upscope $end
$upscope $end
$enddefinitions $end
#0
1!
b00000000000000000000000000000000 t
b1 n0
b1 n4
b1 n1
b11111111111111111111111111111101 n2
b00000000000000000000000000001100 n3
b1 n5
b00000000000000000000000000001100 n6
#5
b0 n0
b0 n4
#10
1!
b00000000000000000000000000000001 t
b1 n0
b1 n4
b0 n1
b00000000000000000000000000000000 n2
b00000000000000000000000000000000 n3
b0 n5
b00000000000000000000000000000000 n6
#15
b0 n0
b0 n4
#20
1!
b00000000000000000000000000000010 t
b1 n0
b1 n4
b0 n1
b00000000000000000000000000000001 n2
b00000000000000000000000000000001 n3
b0 n5
b00000000000000000000000000000001 n6
#25
b0 n0
b0 n4
#30
1!
b00000000000000000000000000000011 t
b1 n0
b1 n4
b0 n1
b00000000000000000000000000000010 n2
b00000000000000000000000000000010 n3
b0 n5
b00000000000000000000000000000010 n6
#35
b0 n0
b0 n4
#40
1!
b00000000000000000000000000000100 t
b1 n0
b1 n4
b0 n1
b00000000000000000000000000000011 n2
b00000000000000000000000000000011 n3
b0 n5
b00000000000000000000000000000011 n6
#45
b0 n0
b0 n4
#50
1!
b00000000000000000000000000000101 t
b1 n0
b1 n4
b0 n1
b00000000000000000000000000000100 n2
b00000000000000000000000000000100 n3
b0 n5
b00000000000000000000000000000100 n6
#55
b0 n0
b0 n4
#60
1!
b00000000000000000000000000000110 t
b1 n0
b1 n4
b0 n1
b00000000000000000000000000000101 n2
b00000000000000000000000000000101 n3
b0 n5
b00000000000000000000000000000101 n6
#65
b0 n0
b0 n4
#70
1!
b00000000000000000000000000000111 t
b1 n0
b1 n4
b0 n1
b00000000000000000000000000000110 n2
b00000000000000000000000000000110 n3
b0 n5
b00000000000000000000000000000110 n6
#75
b0 n0
b0 n4
#80
1!
b00000000000000000000000000001000 t
b1 n0
b1 n4
b0 n1
b00000000000000000000000000000111 n2
b00000000000000000000000000000111 n3
b0 n5
b00000000000000000000000000000111 n6
#85
b0 n0
b0 n4
#90
1!
b00000000000000000000000000001001 t
b1 n0
b1 n4
b0 n1
b00000000000000000000000000001000 n2
b00000000000000000000000000001000 n3
b0 n5
b00000000000000000000000000001000 n6
#95
b0 n0
b0 n4
#100
1!
b00000000000000000000000000001010 t
b1 n0
b1 n4
b0 n1
b00000000000000000000000000001001 n2
b00000000000000000000000000001001 n3
b0 n5
b00000000000000000000000000001001 n6
#105
b0 n0
b0 n4
#110
1!
b00000000000000000000000000001011 t
b1 n0
b1 n4
b0 n1
b00000000000000000000000000001010 n2
b00000000000000000000000000001010 n3
b0 n5
b00000000000000000000000000001010 n6
#115
b0 n0
b0 n4
#120
1!
b00000000000000000000000000001100 t
b1 n0
b1 n4
b0 n1
b00000000000000000000000000001011 n2
b00000000000000000000000000001011 n3
b0 n5
b00000000000000000000000000001011 n6
#125
b0 n0
b0 n4
#130
1!
b00000000000000000000000000001101 t
b1 n0
b1 n4
b0 n1
b00000000000000000000000000001100 n2
b00000000000000000000000000001100 n3
b0 n5
b00000000000000000000000000001100 n6
#135
b0 n0
b0 n4
#140
1!
b00000000000000000000000000001110 t
b1 n0
b1 n4
b0 n1
b00000000000000000000000000001101 n2
b00000000000000000000000000001101 n3
b0 n5
b00000000000000000000000000001101 n6
#145
b0 n0
b0 n4
#150
1!
b00000000000000000000000000001111 t
b1 n0
b1 n4
b0 n1
b00000000000000000000000000001110 n2
b00000000000000000000000000001110 n3
b0 n5
b00000000000000000000000000001110 n6
#155
b0 n0
b0 n4
#160
1!
b00000000000000000000000000010000 t
b1 n0
b1 n4
b0 n1
b00000000000000000000000000001111 n2
b00000000000000000000000000001111 n3
b0 n5
b00000000000000000000000000001111 n6
#165
b0 n0
b0 n4
#170
1!
b00000000000000000000000000010001 t
b1 n0
b1 n4
b0 n1
b00000000000000000000000000010000 n2
b00000000000000000000000000010000 n3
b0 n5
b00000000000000000000000000010000 n6
#175
b0 n0
b0 n4
#180
1!
b00000000000000000000000000010010 t
b1 n0
b1 n4
b0 n1
b00000000000000000000000000010001 n2
b00000000000000000000000000010001 n3
b0 n5
b00000000000000000000000000010001 n6
#185
b0 n0
b0 n4
#190
1!
b00000000000000000000000000010011 t
b1 n0
b1 n4
b0 n1
b00000000000000000000000000010010 n2
b00000000000000000000000000010010 n3
b0 n5
b00000000000000000000000000010010 n6
#195
b0 n0
b0 n4
#200
1!
b00000000000000000000000000010100 t
b1 n0
b1 n4
b0 n1
b00000000000000000000000000010011 n2
b00000000000000000000000000010011 n3
b0 n5
b00000000000000000000000000010011 n6
#205
b0 n0
b0 n4
#210
1!
b00000000000000000000000000010101 t
b1 n0
b1 n4
b0 n1
b00000000000000000000000000010100 n2
b00000000000000000000000000010100 n3
b0 n5
b00000000000000000000000000010100 n6
#215
b0 n0
b0 n4
#220
1!
b00000000000000000000000000010110 t
b1 n0
b1 n4
b0 n1
b00000000000000000000000000010101 n2
b00000000000000000000000000010101 n3
b0 n5
b00000000000000000000000000010101 n6
#225
b0 n0
b0 n4
#230
1!
b00000000000000000000000000010111 t
b1 n0
b1 n4
b0 n1
b00000000000000000000000000010110 n2
b00000000000000000000000000010110 n3
b0 n5
b00000000000000000000000000010110 n6
#235
b0 n0
b0 n4
#240
1!
b00000000000000000000000000011000 t
b1 n0
b1 n4
b0 n1
b00000000000000000000000000010111 n2
b00000000000000000000000000010111 n3
b0 n5
b00000000000000000000000000010111 n6
#245
b0 n0
b0 n4
#250
1!
b00000000000000000000000000011001 t
b1 n0
b1 n4
b0 n1
b00000000000000000000000000011000 n2
b00000000000000000000000000011000 n3
b0 n5
b00000000000000000000000000011000 n6
#255
b0 n0
b0 n4
#260
1!
b00000000000000000000000000011010 t
b1 n0
b1 n4
b0 n1
b00000000000000000000000000011001 n2
b00000000000000000000000000011001 n3
b0 n5
b00000000000000000000000000011001 n6
#265
b0 n0
b0 n4
#270
1!
b00000000000000000000000000011011 t
b1 n0
b1 n4
b0 n1
b00000000000000000000000000011010 n2
b00000000000000000000000000011010 n3
b0 n5
b00000000000000000000000000011010 n6
#275
b0 n0
b0 n4
#280
1!
b00000000000000000000000000011100 t
b1 n0
b1 n4
b0 n1
b00000000000000000000000000011011 n2
b00000000000000000000000000011011 n3
b0 n5
b00000000000000000000000000011011 n6
#285
b0 n0
b0 n4
#290
1!
b00000000000000000000000000011101 t
b1 n0
b1 n4
b1 n1
b00000000000000000000000000011100 n2
b00000000000000000000000000011100 n3
b1 n5
b00000000000000000000000000011100 n6
#295
b0 n0
b0 n4
#300
1!
b00000000000000000000000000011110 t
b1 n0
b1 n4
b0 n1
b00000000000000000000000000000000 n2
b00000000000000000000000000000000 n3
b0 n5
b00000000000000000000000000000000 n6
#305
b0 n0
b0 n4
#310
1!
b00000000000000000000000000011111 t
b1 n0
b1 n4
